stock_market_bytetheory/SP500History.py
stock_market_bytetheory/SectorIndustryTickerParser.py
stock_market_bytetheory/TickerLevelDataParser.py
stock_market_bytetheory/__init__.py
stock_market_bytetheory/data/SP500_ind.csv
stock_market_bytetheory/data/SP_500.xml
stock_market_bytetheory/data/__init__.py
stock_market_bytetheory-1.0.4.dist-info/LICENSE
stock_market_bytetheory-1.0.4.dist-info/METADATA
stock_market_bytetheory-1.0.4.dist-info/WHEEL
stock_market_bytetheory-1.0.4.dist-info/top_level.txt
stock_market_bytetheory-1.0.4.dist-info/RECORD
