Metadata-Version: 2.1
Name: stock-market-bytetheory
Version: 1.0.4
Summary: Provides some sample stock data and helpers for supporting a stock samples app
Author: Robbie Blom
Classifier: Programming Language :: Python :: 3
Classifier: License :: OSI Approved :: MIT License
Classifier: Operating System :: OS Independent
Requires-Python: >=3.6
License-File: LICENSE
